lib/__init__.py
lib/hello.py
hop_test-1.dist-info/LICENSE
hop_test-1.dist-info/METADATA
hop_test-1.dist-info/WHEEL
hop_test-1.dist-info/top_level.txt
hop_test-1.dist-info/RECORD
